algorithhmicas/__init__.py
algorithhmicas/module1.py
algorithhmicas/post_install.py
algorithhmicas-5.1.dist-info/METADATA
algorithhmicas-5.1.dist-info/WHEEL
algorithhmicas-5.1.dist-info/top_level.txt
algorithhmicas-5.1.dist-info/RECORD
