Metadata-Version: 2.1
Name: algorithhmicas
Version: 5.1
Summary: Description of library
Author: Your Name
Author-email: cinnabonwithcinnamon@email.com
Requires-Dist: numpy
Requires-Dist: requests
